{
    "parent": "block/block",
    "textures": {
        "particle": "computercraft:blocks/cable_core",
        "side": "computercraft:blocks/cable_side"
    },
    "elements": [
        {   
            "from": [ 6, 6, 10 ],
            "to": [ 10, 10, 16 ],
            "faces": {
                "down":  { "uv": [ 6, 0, 10, 6 ], "texture": "#side" },
                "up":    { "uv": [ 6, 10, 10, 16 ], "texture": "#side" },
                "west":  { "uv": [ 0, 6, 6, 10 ], "texture": "#side" },
                "east":  { "uv": [ 10, 6, 16, 10 ], "texture": "#side" }
            }
        }
    ]
}
